newjgreenepack/__init__.py
newjgreenepack/api_client.py
newjgreenepack/configuration.py
newjgreenepack/rest.py
newjgreenepack/api/__init__.py
newjgreenepack/api/pets_api.py
newjgreenepack/models/__init__.py
newjgreenepack/models/error.py
newjgreenepack/models/pet.py
newjgreenepack/models/pets.py
test/__init__.py
test/test_error.py
test/test_pet.py
test/test_pets.py
test/test_pets_api.py
newjgreenepack-0.12.1.dist-info/METADATA
newjgreenepack-0.12.1.dist-info/WHEEL
newjgreenepack-0.12.1.dist-info/top_level.txt
newjgreenepack-0.12.1.dist-info/RECORD
